tictactoc/__init__.py
tictactoc/plot.py
tictactoc/tictactoc.py
tictactoc/tests/__init__.py
tictactoc/tests/test_plot.py
tictactoc/tests/test_tictactoc.py
tictactoc-0.3.1.dist-info/entry_points.txt
tictactoc-0.3.1.dist-info/WHEEL
tictactoc-0.3.1.dist-info/METADATA
tictactoc-0.3.1.dist-info/RECORD
